source_alpha_vantage/__init__.py
source_alpha_vantage/manifest.yaml
source_alpha_vantage/object_dpath_extractor.py
source_alpha_vantage/run.py
source_alpha_vantage/schemas/quote.json
source_alpha_vantage/schemas/time_series_daily.json
source_alpha_vantage/schemas/time_series_daily_adjusted.json
source_alpha_vantage/schemas/time_series_intraday.json
source_alpha_vantage/schemas/time_series_monthly.json
source_alpha_vantage/schemas/time_series_monthly_adjusted.json
source_alpha_vantage/schemas/time_series_weekly.json
source_alpha_vantage/schemas/time_series_weekly_adjusted.json
source_alpha_vantage/source.py
source_alpha_vantage/spec.yaml
airbyte_source_alpha_vantage-0.1.30.dist-info/METADATA
airbyte_source_alpha_vantage-0.1.30.dist-info/WHEEL
airbyte_source_alpha_vantage-0.1.30.dist-info/entry_points.txt
airbyte_source_alpha_vantage-0.1.30.dist-info/RECORD
